s3_fetcher/__init__.py
s3_fetcher/cli.py
s3_fetcher/data_manager.py
s3_fetcher-0.1.1.dist-info/METADATA
s3_fetcher-0.1.1.dist-info/WHEEL
s3_fetcher-0.1.1.dist-info/entry_points.txt
s3_fetcher-0.1.1.dist-info/top_level.txt
s3_fetcher-0.1.1.dist-info/RECORD
